fastui_chat/__init__.py
fastui_chat/app.py
fastui_chat/chat.py
fastui_chat/components.py
fastui_chat/history.py
fastui_chat/py.typed
fastui_chat/runtime.py
fastui_chat/session.py
fastui_chat-0.3.4.dist-info/METADATA
fastui_chat-0.3.4.dist-info/WHEEL
fastui_chat-0.3.4.dist-info/licenses/LICENSE
fastui_chat-0.3.4.dist-info/RECORD
