Metadata-Version: 2.1
Name: fastui-chat
Version: 0.3.4
Summary: Minimalistic chatbot ui using fastapi, fastui and langchain.
Author-email: Shroominic <contact@shroominic.com>
License-Expression: MIT
License-File: LICENSE
Classifier: Development Status :: 4 - Beta
Classifier: Intended Audience :: Developers
Classifier: License :: OSI Approved :: MIT License
Classifier: Programming Language :: Python :: 3
Classifier: Programming Language :: Python :: 3 :: Only
Classifier: Programming Language :: Python :: 3.10
Classifier: Programming Language :: Python :: 3.11
Classifier: Programming Language :: Python :: 3.12
Classifier: Topic :: Software Development :: Libraries :: Python Modules
Requires-Python: >=3.10
Requires-Dist: fastui[fastapi]>=0.4
Requires-Dist: funcchain>=0.3.1
